peako/__init__.py
peako/peako_snakemake_wrapper.py
peako/version.py
peako/data/add-pooled-de-novo-motifs-centrimo.py
peako/data/centrimo-neg-environment.yml
peako/data/macs2-environment.yml
peako/data/meme510-env.yml
peako/data/meme510cf-env.yml
peako/data/meme511-env.yml
peako/data/peako-only.py
peako/data/pool-de-novo-motifs-before-centrimo.py
peako/data/py273-environment-meme412.yml
peako/data/py273-environment-meme505.yml
peako/data/py273-environment-py3.yml
peako/data/py273-environment.yml
peako/data/run_MEME-ChIP.sh
peako/data/snakefile
peako-0.0.6.dist-info/LICENSE
peako-0.0.6.dist-info/METADATA
peako-0.0.6.dist-info/WHEEL
peako-0.0.6.dist-info/entry_points.txt
peako-0.0.6.dist-info/top_level.txt
peako-0.0.6.dist-info/RECORD
