Metadata-Version: 2.1
Name: peako
Version: 0.0.6
Summary: A package for discovering motifs in ChIP-seq datasets with knockout controls
Home-page: https://github.com/hoffmangroup/peako
Author: Danielle Denisko
Author-email: danielle.denisko@mail.utoronto.ca
License: GPLv3
Platform: UNKNOWN
